pinyin_rhymer/__init__.py
pinyin_rhymer/consonant.py
pinyin_rhymer/data/convert.py
pinyin_rhymer/data/pinyin_list.csv
pinyin_rhymer/data/pinyin_list.py
pinyin_rhymer/data/pinyin_list.txt
pinyin_rhymer/error.py
pinyin_rhymer/pinyin.py
pinyin_rhymer/rhyme_scheme.py
pinyin_rhymer/vowel.py
pinyin_rhymer-0.1.9.dist-info/LICENSE
pinyin_rhymer-0.1.9.dist-info/WHEEL
pinyin_rhymer-0.1.9.dist-info/METADATA
pinyin_rhymer-0.1.9.dist-info/RECORD
