Metadata-Version: 2.1
Name: pinyin-rhymer
Version: 0.1.9
Summary: Generate pinyin rhymes based on rhyme schemes.
Author: RCJacH
Author-email: RCJacH@outlook.com
Requires-Python: >=3.10,<4.0
Classifier: Programming Language :: Python :: 3
Classifier: Programming Language :: Python :: 3.10
